Metadata-Version: 2.1
Name: hive-networkx
Version: 2023.8.22
Summary: Hive plots in Python
Home-page: https://github.com/jolespin/hive_networkx
Author: Josh L. Espinoza
Author-email: jespinoz@jcvi.org
License: BSD-3
License-File: LICENSE
